graiax/text2img/playwright/__init__.py
graiax/text2img/playwright/converter.py
graiax/text2img/playwright/css/__init__.py
graiax/text2img/playwright/css/container.css
graiax/text2img/playwright/css/github.css
graiax/text2img/playwright/css/one-dark.css
graiax/text2img/playwright/css/reset.css
graiax/text2img/playwright/plugins/__init__.py
graiax/text2img/playwright/plugins/code/__init__.py
graiax/text2img/playwright/plugins/code/highlight_lines.py
graiax/text2img/playwright/plugins/code/highlighter.py
graiax/text2img/playwright/plugins/code/language_resolver.py
graiax/text2img/playwright/plugins/container.py
graiax/text2img/playwright/renderer.py
graiax/text2img/playwright/utils.py
graiax_text2img_playwright-0.5.0.dist-info/METADATA
graiax_text2img_playwright-0.5.0.dist-info/WHEEL
graiax_text2img_playwright-0.5.0.dist-info/licenses/LICENSE
graiax_text2img_playwright-0.5.0.dist-info/RECORD
