Metadata-Version: 2.1
Name: graiax-text2img-playwright
Version: 0.5.0
Summary: 基于 Playwright 的适用于 Graia 的文转图工具
Keywords: graia graiax text2img playwright
Author-Email: Redlnn <w731347477@gmail.com>, BlueGlassBlock <blueglassblock@outlook.com>
License: MIT
Classifier: Typing :: Typed
Classifier: Development Status :: 4 - Beta
Classifier: Programming Language :: Python :: 3
Classifier: Programming Language :: Python :: 3.10
Classifier: Programming Language :: Python :: 3.11
Classifier: Programming Language :: Python :: 3.12
Project-URL: Repository, https://github.com/GraiaCommunity/graiax-text2img-playwright
Requires-Python: >=3.10
Requires-Dist: graiax-playwright>=0.4.1
Requires-Dist: markdown-it-py[linkify,plugins]>=3.0.0
Requires-Dist: pygments>=2.17.2
Requires-Dist: mdit-py-emoji>=0.1.1
